real2tex.py
real2tex-1.0.2.dist-info/LICENSE
real2tex-1.0.2.dist-info/METADATA
real2tex-1.0.2.dist-info/WHEEL
real2tex-1.0.2.dist-info/top_level.txt
real2tex-1.0.2.dist-info/RECORD
