Metadata-Version: 2.1
Name: real2tex
Version: 1.0.2
Summary: Converts a number to a LaTeX string in scientific notation.
Author: Giuseppe Scarlato
Project-URL: Homepage, https://github.com/Giuseppe499/real2tex
Project-URL: Issues, https://github.com/Giuseppe499/real2tex/issues
Classifier: Programming Language :: Python :: 3
Classifier: License :: OSI Approved :: GNU General Public License v3 (GPLv3)
Classifier: Operating System :: OS Independent
Requires-Python: >=3.0
License-File: LICENSE
